apd/sensors/__init__.py
apd/sensors/base.py
apd/sensors/cli.py
apd/sensors/database.py
apd/sensors/exceptions.py
apd/sensors/py.typed
apd/sensors/sensors.py
apd/sensors/third_party_wsgi.py
apd/sensors/utils.py
apd/sensors/wsgi_simple.py
apd/sensors/alembic/env.py
apd/sensors/alembic/versions/0eeb2a54fea8_add_initial_sensor_table.py
apd/sensors/wsgi/__init__.py
apd/sensors/wsgi/base.py
apd/sensors/wsgi/serve.py
apd/sensors/wsgi/v10.py
apd/sensors/wsgi/v20.py
apd/sensors/wsgi/v21.py
apd/sensors/wsgi/v30.py
apd.sensors-2.2.1.dist-info/LICENCE
apd.sensors-2.2.1.dist-info/METADATA
apd.sensors-2.2.1.dist-info/WHEEL
apd.sensors-2.2.1.dist-info/entry_points.txt
apd.sensors-2.2.1.dist-info/top_level.txt
apd.sensors-2.2.1.dist-info/RECORD
