Metadata-Version: 2.1
Name: apd.sensors
Version: 2.2.1
Summary: APD Sensor package
Home-page: UNKNOWN
License: MIT
Keywords: iot
Platform: UNKNOWN
Classifier: Programming Language :: Python :: 3
Classifier: Programming Language :: Python :: 3.7
Classifier: Programming Language :: Python :: 3.8
Requires-Dist: psutil
Requires-Dist: click
Requires-Dist: pint
Requires-Dist: adafruit-circuitpython-dht ; "arm" in platform_machine
Provides-Extra: scheduled
Requires-Dist: sqlalchemy ; extra == 'scheduled'
Requires-Dist: alembic ; extra == 'scheduled'
Provides-Extra: storedapi
Requires-Dist: flask-sqlalchemy ; extra == 'storedapi'
Requires-Dist: python-dateutil ; extra == 'storedapi'
Provides-Extra: webapp
Requires-Dist: flask ; extra == 'webapp'
